:lib: pass:quotes[_library_]
:libs: pass:quotes[_libraries_]
:j: Java
:fs: functies
:f: functie
:m: method
:icons: font
:source-highlighter: rouge

//ifdef::env-github[]
:tip-caption: :bulb:
:note-caption: :information_source:
:important-caption: :heavy_exclamation_mark:
:caution-caption: :fire:
:warning-caption: :warning:
//endif::[]

= Programmeren
//Author Mark Nuyts
//v0.1
:toc: left
:toclevels: 4

== Programmeertaal

=== Opdrachten voor de computer

Een computer is een logische machine die we opdrachten kunnen geven.

Voorbeelden van opdrachten:

* Schrijf iets weg naar een bestand op de ssd.
* Krijg een lijst van de bestanden op de hdd.
* Toon iets op het scherm.
* Haal een pagina op van het internet via het ethernet netwerk.
* Tel 2 getallen op en sla het op in een variabele x.

Opdrachten worden gegeven via een programma.
De computer bestaat uit verschillende onderdelen. Het is de CPU of centrale rekeneenheid die het programma interpreteerd.

image::motherboard.webp[De onderdelen van een moederbord.]

Opdrachten geven aan een computer kan via een programma.
Met een programmeertaal kan een programma geschreven worden.



=== CPU Instructieset

Iedere computer CPU heeft een bepaalde architectuur of ontwerp.
Hier zijn heel wat standaarden in: 

* x86 (32bit)
+
image::x86.jpg[x86 cpu]
+
* x64 (64bit)
+
image::AMD_Opteron_146_Venus,_2005.jpg[x64 cpu]
+
* ARM
+
image::arm.webp[ARM cpu]
+
* RISC
+
image::KL_Sun_UltraSparc.jpg[SUN Sparc RISC cpu]
+
* Mainframe
+
image::mainframe1.jpg[mainframe]
+
image::mainframe.jpg[modern mainframe]


Aan deze standaarden van CPU's kunnen opdrachten gegeven worden via **de instructieset**, dit is de machinetaal.
Dit zijn afgesproken opdrachten op een laag niveau (vb. onthoud een getal, tel een getal op, haal een waarde op van de ssd, ...)

Deze opdrachten via de instructieset kunnen in een laag niveau computertaal worden voorgesteld, namelijk __assembly__:


image::assembly.jpeg[Assembly en machinetaal]

Dit is een **zeer ingewikkelde manier om te programmeren**.

Gelukkig zijn er hoog niveau programmeertalen ontwikkeld die het ons gemakkelijker maken.


=== Hoog niveau programmeertalen

Hoog niveau programmeertalen (die makkelijker zijn om te schrijven), kunnen via ##compilatie## automatisch omgezet worden naar machinetaal.

**Tekst -> compilatie -> machinetaal voor een specifieke architectuur**

De machinetaal wordt bijgehouden in een uitvoerbaar bestand of __executable (iets waarop je kan dubbelklikken om het programma te openen).

=== Voorbeelden van computeropdrachten

* assembly of machinetaal
* Idem in C
* Idem in Java


== Programmeertalen: Een historisch overzicht

image::History_of_object-oriented_programming_languages.svg[]

Mainframe
c
c++
C#
Java
Kotlin, Groovy
Perl
Python
Php
Rust

== Java

In deze cursus programmeren werken we met de programmeertaal Java.
Dit heeft enkele redenen:

* Java is **__open source__**, je kan het dus gratis gebruiken zonder te betalen voor licenties.
* Java is een **krachtige programmeertaal**.
* Het is **Object georienteerd** en werkt naast functies ook met klassen.
* Java is een **multiplatform** programmeertaal, eenmaal gecompileerd werkt het op zowel Windows, Linux, MacOSX, Mainframes, BSD, ...
* Java is deels een **functionele programmeertaal**, naast object georienteerd ( en dus een multi-paradigme programmeertaal).
* In het **bedrijfsleven** is Java populair.
* Java maakt van veel concepten gebruik die ook in andere programmeertalen voorkomen. Eenmaal je Java beheerst, kan je eenvoudig overschakelen naar andere talen.

== Java

Java werd ontwikkeld om de nadelen van voorgaande talen weg te werken.
De populaire C taal had de volgende nadelen:

* Het was complex om te schrijven, je moest rekening houden met het geheugenbeheer (variabelen verwijderen)
* Je moest voor elke computerarchitectuur hercompileren.

Java moest dus:

* Eenvoudiger zijn om te schrijven.
* Multiplatform zijn.

Java heeft deze 2 problemen opgelost door een tussenliggende ##virtuele machine## te ontwikkelen.
Deze JVM (Java virtuele machine) is een processor die virtueel draait als een programma op je echte processor.
Dezelfde JVM kan men laten draaien op alle verschillende computerarchitecturen.

image::jvm.png[]


##Het volstaat dus 1x te compileren naar de instructieset van de virtuele machine, deze heet **bytecode**##.
Vervolgens kan elke computerarchitectuur deze JVM opstarten en het gecompileerde programma starten.

Op de JVM draait periodiek (met een bepaald interval) een ##__garbage collector__## of een afvalopruimer.
Deze verwijderd ongebruikte variabelen. Hierdoor moet je in Java geen rekening meer houden met het geheugenbeheer.

Het grote nadeel van deze aanpak is dat Java wat trager is dan C:

* De JVM neemt wat __computerresources__ in beslag.
* Om de zoveel tijd moet de __garbage collector__ zijn werk doen.

=== Java schrijven (of programmeren)

{j} wordt geschreven in een tekst document.
Dit tekst document heeft de .java extensie. 
Bijvoorbeeld: MijnJavaBestand.java .
Dit tekstbestand bevat gewone tekst (woorden bestaande uit karakters).
De tekst die je schrijft moet wel voldoen aan de ##syntax## van de taal.

==== De syntax

Iedere programmeertaal bestaat uit een syntax.
Dit zijn een reeks afspraken van de taal:

. Welke woorden kunnen gebruikt worden? In Java mag een woord bijvoorbeeld niet beginnen met een cijfer.
. welke woorden zijn gereserveerd door de programmeertaal? Bijvoorbeeld het __public__ woord.
. Op welke plaats mogen deze woorden staan?
. Welke scheidingskarakters worden toegestaan of verplicht? Java verplicht bijvoorbeeld _;_ na elke regel.
. Hoe belangrijk is indentatie?

Om succesvol te programmeren dien je de syntax van een taal te kennen.

De syntax bepaalt hoe statements, variabelen, functies en klassen geschreven moeten worden.

=== Java compileren naar bytecode

Een voorbeeld Java programma:

[source, java]
----
public class HelloWorld {
	public static void main(String[] args) {
		System.out.println("Hello World");
	}
}
----

Na het schrijven van een programma, dienen we het nog te compileren naar bytecode.
De bytecode kan door de JVM ingelezen worden.

Dit gaat als volgt te werk:

[source]
----
javac Helloworld.java
----

__java##c##__ is het commando voor de java ##c##ompiler.
Dit proces produceert bytecode, bytecode staat altijd in een .class bestand:

[source]
----
javac Helloworld.class
----

Voorbeeld bytecode van de Helloworld.class:

[source]
----
Compiled from "HelloWorld.java"
public class HelloWorld extends java.lang.Object
  SourceFile: "HelloWorld.java"
  minor version: 0
  major version: 50
  Constant pool:
const #1 = Method	#6.#15;	//  java/lang/Object."<init>":()V
const #2 = Field	#16.#17;	//  java/lang/System.out:Ljava/io/PrintStream;
const #3 = String	#18;	//  Hello World
const #4 = Method	#19.#20;	//  java/io/PrintStream.println:(Ljava/lang/String;)V
const #5 = class	#21;	//  HelloWorld
const #6 = class	#22;	//  java/lang/Object
const #7 = Asciz	<init>;
const #8 = Asciz	()V;
const #9 = Asciz	Code;
const #10 = Asciz	LineNumberTable;
const #11 = Asciz	main;
const #12 = Asciz	([Ljava/lang/String;)V;
const #13 = Asciz	SourceFile;
const #14 = Asciz	HelloWorld.java;
const #15 = NameAndType	#7:#8;//  "<init>":()V
const #16 = class	#23;	//  java/lang/System
const #17 = NameAndType	#24:#25;//  out:Ljava/io/PrintStream;
const #18 = Asciz	Hello World;
const #19 = class	#26;	//  java/io/PrintStream
const #20 = NameAndType	#27:#28;//  println:(Ljava/lang/String;)V
const #21 = Asciz	HelloWorld;
const #22 = Asciz	java/lang/Object;
const #23 = Asciz	java/lang/System;
const #24 = Asciz	out;
const #25 = Asciz	Ljava/io/PrintStream;;
const #26 = Asciz	java/io/PrintStream;
const #27 = Asciz	println;
const #28 = Asciz	(Ljava/lang/String;)V;
 
{
public HelloWorld();
  Code:
   Stack=1, Locals=1, Args_size=1
   0:	aload_0
   1:	invokespecial	#1; //Method java/lang/Object."<init>":()V
   4:	return
  LineNumberTable: 
   line 2: 0
 
 
public static void main(java.lang.String[]);
  Code:
   Stack=2, Locals=1, Args_size=1
   0:	getstatic	#2; //Field java/lang/System.out:Ljava/io/PrintStream;
   3:	ldc	#3; //String Hello World
   5:	invokevirtual	#4; //Method java/io/PrintStream.println:(Ljava/lang/String;)V
   8:	return
  LineNumberTable: 
   line 9: 0
   line 10: 8
}
----

[IMPORTANT]
----
Bytecode is de machinetaal voor de Java virtuele machine. Dit is geen leesbare taal (binaire instructies).
----

image::java-virtual-machine.png[]

=== Bytecode uitvoeren met de virtuele machine

De JVM voert bytecode uit op de onderliggende CPU.
Om gebruik te maken van de JVM, gebruiken we het __java__ commando op het .class (bytecode) bestand:

[source]
----
java Helloworld.class
----

Dit voert het geschreven programma uit. De output wordt naar de console (het __command prompt__ scherm) geschreven:

[source]
----
Hello World
----
